README.rst
setup.py
pygments_solarized_style/__init__.py
pygments_solarized_style/dark.py
pygments_solarized_style/light.py
pygments_solarized_style.egg-info/PKG-INFO
pygments_solarized_style.egg-info/SOURCES.txt
pygments_solarized_style.egg-info/dependency_links.txt
pygments_solarized_style.egg-info/entry_points.txt
pygments_solarized_style.egg-info/not-zip-safe
pygments_solarized_style.egg-info/requires.txt
pygments_solarized_style.egg-info/top_level.txt