Metadata-Version: 1.0
Name: pygments-solarized-style
Version: 0.1
Summary: Pygments version of the Solarized theme.
Home-page: https://github.com/lordjx/pygments-solarized_style
Author: Jason Xu
Author-email: hongyi.xu@gmail.com
License: MIT
Keywords: pygments,style,solarized,syntax highlighting
Platform: UNKNOWN
